LICENSE
MANIFEST.in
README.rst
metadata.py
setup.py
cms_search/__init__.py
cms_search/cms_app.py
cms_search/models.py
cms_search/search_indexes.py
cms_search/settings.py
cms_search/search_helpers/__init__.py
cms_search/search_helpers/fields.py
cms_search/search_helpers/indexes.py
cms_search/search_helpers/models.py
cms_search/search_helpers/templatetags/__init__.py
cms_search/search_helpers/templatetags/cms_search_tags.py
django_cms_search.egg-info/PKG-INFO
django_cms_search.egg-info/SOURCES.txt
django_cms_search.egg-info/dependency_links.txt
django_cms_search.egg-info/not-zip-safe
django_cms_search.egg-info/requires.txt
django_cms_search.egg-info/top_level.txt
docs/Makefile
docs/conf.py
docs/index.rst
docs/make.bat
docs/_build/doctrees/environment.pickle
docs/_build/doctrees/index.doctree
docs/_build/html/.buildinfo
docs/_build/html/genindex.html
docs/_build/html/index.html
docs/_build/html/objects.inv
docs/_build/html/py-modindex.html
docs/_build/html/search.html
docs/_build/html/searchindex.js
docs/_build/html/_sources/index.txt
docs/_build/html/_static/ajax-loader.gif
docs/_build/html/_static/basic.css
docs/_build/html/_static/comment-bright.png
docs/_build/html/_static/comment-close.png
docs/_build/html/_static/comment.png
docs/_build/html/_static/default.css
docs/_build/html/_static/doctools.js
docs/_build/html/_static/down-pressed.png
docs/_build/html/_static/down.png
docs/_build/html/_static/file.png
docs/_build/html/_static/jquery.js
docs/_build/html/_static/minus.png
docs/_build/html/_static/plus.png
docs/_build/html/_static/pygments.css
docs/_build/html/_static/searchtools.js
docs/_build/html/_static/sidebar.js
docs/_build/html/_static/underscore.js
docs/_build/html/_static/up-pressed.png
docs/_build/html/_static/up.png
docs/_build/html/_static/websupport.js
docs/_ext/djangorefs.py