Metadata-Version: 1.1
Name: django-cms-search
Version: 0.6.3
Summary: An extension to django CMS to provide multilingual Haystack indexes
Home-page: http://github.com/piquadrat/django-cms-search
Author: Benjamin Wohlwend
Author-email: piquadrat@gmail.com
License: BSD
Platform: OS Independent
Classifier: Development Status :: 4 - Beta
Classifier: Framework :: Django
Classifier: Intended Audience :: Developers
Classifier: License :: OSI Approved :: BSD License
Classifier: Operating System :: OS Independent
Classifier: Programming Language :: Python
Classifier: Topic :: Internet :: WWW/HTTP
